qvenv.py
qvenv-1.2.0.dist-info/licenses/LICENSE
qvenv-1.2.0.dist-info/METADATA
qvenv-1.2.0.dist-info/WHEEL
qvenv-1.2.0.dist-info/entry_points.txt
qvenv-1.2.0.dist-info/top_level.txt
qvenv-1.2.0.dist-info/RECORD
