Metadata-Version: 2.4
Name: qvenv
Version: 1.2.0
Summary: A beautiful command-line tool for managing Python virtual environments with automatic activation and recursive search
Author-email: Griffin Strier <griffincancode@gmail.com>
License: MIT
Project-URL: Homepage, https://github.com/GriffinCanCode/QVenv
Project-URL: Bug Reports, https://github.com/GriffinCanCode/QVenv/issues
Project-URL: Source, https://github.com/GriffinCanCode/QVenv
Keywords: virtualenv,venv,environment,python,packaging,development
Classifier: Development Status :: 5 - Production/Stable
Classifier: Intended Audience :: Developers
Classifier: Topic :: Software Development :: Build Tools
Classifier: License :: OSI Approved :: MIT License
Classifier: Programming Language :: Python :: 3
Classifier: Programming Language :: Python :: 3.6
Classifier: Programming Language :: Python :: 3.7
Classifier: Programming Language :: Python :: 3.8
Classifier: Programming Language :: Python :: 3.9
Classifier: Programming Language :: Python :: 3.10
Classifier: Programming Language :: Python :: 3.11
Classifier: Programming Language :: Python :: 3.12
Classifier: Operating System :: OS Independent
Classifier: Environment :: Console
Requires-Python: >=3.6
License-File: LICENSE
Requires-Dist: rich>=10.0.0
Dynamic: license-file
